swprocess/__init__.py
swprocess/activetimeseries.py
swprocess/array1d.py
swprocess/hvsr.py
swprocess/interact.py
swprocess/inversion.py
swprocess/masw.py
swprocess/maswworkflows.py
swprocess/meta.py
swprocess/peaks.py
swprocess/peaks_suite.py
swprocess/peakssuite.py
swprocess/postprocess.py
swprocess/process.py
swprocess/regex.py
swprocess/register.py
swprocess/sensor1c.py
swprocess/snr.py
swprocess/source.py
swprocess/spaccurve.py
swprocess/spaccurvesuite.py
swprocess/stats.py
swprocess/utils.py
swprocess/wavefieldtransform1d.py
swprocess/wavefieldtransforms.py
swprocess-0.3.0.dist-info/LICENSE.txt
swprocess-0.3.0.dist-info/METADATA
swprocess-0.3.0.dist-info/WHEEL
swprocess-0.3.0.dist-info/top_level.txt
swprocess-0.3.0.dist-info/RECORD
