Metadata-Version: 2.1
Name: swprocess
Version: 0.3.0
Summary: Package for Surface Wave Processing
Home-page: https://github.com/jpvantassel/swprocess
Author: Joseph P. Vantassel
Author-email: joseph.p.vantassel@gmail.com
Project-URL: Bug Reports, https://github.com/jpvantassel/swprocess/issues
Project-URL: Source, https://github.com/jpvantassel/swprocess
Project-URL: Docs, https://swprocess.readthedocs.io/en/latest/?badge=latest
Keywords: surface-wave dispersion processing geopsy active passive masw mam
Classifier: Development Status :: 4 - Beta
Classifier: Intended Audience :: Education
Classifier: Intended Audience :: Science/Research
Classifier: Topic :: Education
Classifier: Topic :: Scientific/Engineering
Classifier: Topic :: Scientific/Engineering :: Physics
Classifier: License :: OSI Approved :: GNU General Public License v3 or later (GPLv3+)
Classifier: Programming Language :: Python :: 3.8
Classifier: Programming Language :: Python :: 3.9
Classifier: Programming Language :: Python :: 3.10
Classifier: Programming Language :: Python :: 3.11
Classifier: Programming Language :: Python :: 3.12
Requires-Python: >=3.8
License-File: LICENSE.txt
Requires-Dist: numpy
Requires-Dist: scipy
Requires-Dist: matplotlib
Requires-Dist: obspy
Requires-Dist: sigpropy (>=1.0.0)
Requires-Dist: pandas
Requires-Dist: swprepost
Requires-Dist: PyQt5
Provides-Extra: dev
Requires-Dist: coverage ; extra == 'dev'
Requires-Dist: tox ; extra == 'dev'
Requires-Dist: sphinx ; extra == 'dev'
Requires-Dist: sphinx-rtd-theme ; extra == 'dev'
Requires-Dist: jupyterlab ; extra == 'dev'
